zenitai/__init__.py
zenitai/experiment/__init__.py
zenitai/experiment/experiment.py
zenitai/transform/__init__.py
zenitai/transform/_woe.py
zenitai/utils/__init__.py
zenitai/utils/functions.py
zenitai/utils/metrics.py
zenitai/utils/tests.py
zenitai/utils/utils.py
ZenitAI-0.6.2.dist-info/LICENSE.md
ZenitAI-0.6.2.dist-info/METADATA
ZenitAI-0.6.2.dist-info/WHEEL
ZenitAI-0.6.2.dist-info/top_level.txt
ZenitAI-0.6.2.dist-info/RECORD
