Metadata-Version: 2.1
Name: ZenitAI
Version: 0.6.2
Summary: Tools for ML
Home-page: https://github.com/CEM3H/zenit-ai
Author: Stepan Kadochnikov
Author-email: kadochnikov.sv@gmail.com
License: UNKNOWN
Project-URL: Bug Tracker, https://github.com/CEM3H/zenit-ai/issues
Platform: UNKNOWN
Classifier: Programming Language :: Python :: 3
Classifier: License :: OSI Approved :: MIT License
Classifier: Operating System :: OS Independent
Requires-Python: >=3.6
License-File: LICENSE.md
